mmcc_framework/__init__.py
mmcc_framework/activity.py
mmcc_framework/callback_adapters.py
mmcc_framework/exceptions.py
mmcc_framework/framework.py
mmcc_framework/nlu_adapters.py
mmcc_framework/process.py
mmcc_framework/response.py
mmcc_framework/validation.py
mmcc_framework-0.3.2.dist-info/LICENSE.txt
mmcc_framework-0.3.2.dist-info/METADATA
mmcc_framework-0.3.2.dist-info/WHEEL
mmcc_framework-0.3.2.dist-info/top_level.txt
mmcc_framework-0.3.2.dist-info/RECORD
