Metadata-Version: 2.1
Name: mmcc-framework
Version: 0.3.2
Summary: Create a multimodal chatbot modeled on a process
Home-page: UNKNOWN
Author: Giubots
License: UNKNOWN
Platform: UNKNOWN
Classifier: Intended Audience :: Developers
Classifier: License :: OSI Approved :: GNU General Public License v3 (GPLv3)
Classifier: Programming Language :: Python :: 3
Classifier: Operating System :: OS Independent
Requires-Python: >=3.6
